cver/__init__.py
cver/__main__.py
cver/scraper.py
cver-1.0.0.dist-info/METADATA
cver-1.0.0.dist-info/WHEEL
cver-1.0.0.dist-info/dependency_links.txt
cver-1.0.0.dist-info/entry_points.txt
cver-1.0.0.dist-info/top_level.txt
cver-1.0.0.dist-info/RECORD
